get_version.py
euxfel_extra-2025.1.dist-info/WHEEL
euxfel_extra-2025.1.dist-info/top_level.txt
euxfel_extra-2025.1.dist-info/RECORD
euxfel_extra-2025.1.dist-info/METADATA
euxfel_extra-2025.1.dist-info/licenses/LICENSE
extra/__init__.py
extra/__version__.py
extra/calibration.py
extra/signal/_interpolation.pyx
extra/signal/_interpolation.cpython-310-x86_64-linux-gnu.so
extra/signal/_ftd.c
extra/signal/_ftd.pyx
extra/signal/_interpolation.c
extra/signal/__init__.py
extra/signal/_ftd.cpython-310-x86_64-linux-gnu.so
extra/components/_adq.cpython-310-x86_64-linux-gnu.so
extra/components/las.py
extra/components/adq.py
extra/components/scan.py
extra/components/_adq.c
extra/components/scantool.py
extra/components/__init__.py
extra/components/pulses.py
extra/components/xgm.py
extra/components/_adq.pyx
extra/components/timepix.py
extra/components/detector_motors.py
extra/components/dld.py
extra/components/utils.py
extra/recipes/base.py
extra/recipes/cookiebox.py
extra/recipes/vs_utils.py
extra/recipes/__init__.py
extra/recipes/cookiebox_deconvolve.py
extra/recipes/grating.py
extra/recipes/vs.py
extra/data/__init__.py
extra/data/components.py
extra/damnit/__init__.py
extra/karabo_bridge/__init__.py
extra/utils/misc.py
extra/utils/functions.py
extra/utils/__init__.py
extra/geom/__init__.py
