Metadata-Version: 2.4
Name: euxfel-EXtra
Version: 2025.1
Summary: European XFEL toolkit for research and analysis
Author-email: European XFEL <da@xfel.eu>
License: BSD-3-Clause
Project-URL: Homepage, https://github.com/European-XFEL/EXtra
Project-URL: Documentation, https://extra.readthedocs.io/en/latest/
Classifier: Development Status :: 3 - Alpha
Classifier: Intended Audience :: Developers
Classifier: Intended Audience :: Science/Research
Classifier: License :: OSI Approved :: BSD License
Classifier: Operating System :: POSIX :: Linux
Classifier: Topic :: Scientific/Engineering :: Information Analysis
Classifier: Topic :: Scientific/Engineering :: Physics
Requires-Python: >=3.10
License-File: LICENSE
Requires-Dist: damnit
Requires-Dist: euxfel_bunch_pattern
Requires-Dist: extra_data>=1.13
Requires-Dist: extra_geom
Requires-Dist: h5py
Requires-Dist: karabo_bridge
Requires-Dist: lmfit
Requires-Dist: oauth2-xfel-client>=6.1
Requires-Dist: pandas
Requires-Dist: xarray
Requires-Dist: mpl_interactions
Requires-Dist: pasha
Requires-Dist: pint
Requires-Dist: requests
Requires-Dist: scipy
Requires-Dist: tabulate
Provides-Extra: test
Requires-Dist: pytest; extra == "test"
Requires-Dist: pytest-cov; extra == "test"
Requires-Dist: pytest-recording; extra == "test"
Provides-Extra: docs
Requires-Dist: mkdocs-material; extra == "docs"
Requires-Dist: mkdocstrings; extra == "docs"
Requires-Dist: mkdocstrings-python>=1.2.0; extra == "docs"
Requires-Dist: pymdown-extensions; extra == "docs"
Dynamic: license-file
